<?xml version="1.0" encoding="GBK" standalone="no"?>
<Root>
	<Head>
		<TranCode>2015004</TranCode>
		<ChannelDate>2015-10-01 13:21:59</ChannelDate>
	</Head>
	<Data>
		<yhzh>6228480058063832073</yhzh>
		<yhmc>徐海才</yhmc>
		<GhId>09982332</GhId>
		<IdCard>420528198704163819</IdCard>
		<PatientId>88888888</PatientId>
		<UserId>JQM0001</UserId>
		<CardTypeID>01</CardTypeID>
		<Bills>
			<Bill>
				<ReceiptNo>0001561251</ReceiptNo>
				<ReceiptTime>2015-09-10 09:04:24</ReceiptTime>
				<BillDept>骨一科</BillDept>
				<Doctor>熊家亭</Doctor>
				<ShouldMoney>15</ShouldMoney>
				<ActualMoney>15</ActualMoney>
				<Items>
					<Item>
						<ExecDept>住院西药房</ExecDept>
						<FeesType>自费</FeesType>
						<FeesItem>西药</FeesItem>
						<ItemID>0101002020101</ItemID>
						<ItemName>利福平胶囊1</ItemName>
						<ItemUnit>粒</ItemUnit>
						<Num>100</Num>
						<Price>0.15</Price>
						<ShouldMoney_Item>15</ShouldMoney_Item>
						<ActualMoney_Item>15</ActualMoney_Item>
					</Item>
					<Item>
						<ExecDept>住院西药房</ExecDept>
						<FeesType>自费</FeesType>
						<FeesItem>西药</FeesItem>
						<ItemID>0101002020101</ItemID>
						<ItemName>利福平胶囊2</ItemName>
						<ItemUnit>粒</ItemUnit>
						<Num>10</Num>
						<Price>0.15</Price>
						<ShouldMoney_Item>1.5</ShouldMoney_Item>
						<ActualMoney_Item>1.5</ActualMoney_Item>
					</Item>
				</Items>
			</Bill>
			<Bill>
				<ReceiptNo>0001561252</ReceiptNo>
				<ReceiptTime>2015-09-10 09:04:24</ReceiptTime>
				<BillDept>骨一科</BillDept>
				<Doctor>熊家亭</Doctor>
				<ShouldMoney>15</ShouldMoney>
				<ActualMoney>15</ActualMoney>
				<Items>
					<Item>
						<ExecDept>住院西药房</ExecDept>
						<FeesType>自费</FeesType>
						<FeesItem>西药</FeesItem>
						<ItemID>0101002020101</ItemID>
						<ItemName>利福平胶囊A</ItemName>
						<ItemUnit>粒</ItemUnit>
						<Num>100</Num>
						<Price>0.15</Price>
						<ShouldMoney_Item>15</ShouldMoney_Item>
						<ActualMoney_Item>15</ActualMoney_Item>
					</Item>
					<Item>
						<ExecDept>住院西药房</ExecDept>
						<FeesType>自费</FeesType>
						<FeesItem>西药</FeesItem>
						<ItemID>0101002020101</ItemID>
						<ItemName>利福平胶囊B</ItemName>
						<ItemUnit>粒</ItemUnit>
						<Num>100</Num>
						<Price>0.15</Price>
						<ShouldMoney_Item>15</ShouldMoney_Item>
						<ActualMoney_Item>15</ActualMoney_Item>
					</Item>
				</Items>
			</Bill>
		</Bills>
	</Data>
</Root>
